{
  "Timezone": [
    {
      "id": "1",
      "area": "America",
      "city": "Recife"
    },
    {
      "id": "2",
      "area": "Europe",
      "city": "Budapest"
    },
    {
      "area": "Europe",
      "city": "Budapest",
      "id": "RinGeRC"
    },
    {
      "area": "Europe",
      "city": "Barcelona",
      "id": "iwqJncW"
    },
    {
      "area": "Australia",
      "city": "Sydney",
      "id": "8busVzI"
    },
    {
      "area": "America",
      "city": "Caruaru",
      "id": "mPqG_0_"
    }
  ]
}